kurzgesagt/__init__.py
kurzgesagt-1.1.2.dist-info/METADATA
kurzgesagt-1.1.2.dist-info/WHEEL
kurzgesagt-1.1.2.dist-info/top_level.txt
kurzgesagt-1.1.2.dist-info/RECORD
