Metadata-Version: 2.1
Name: kurzgesagt
Version: 1.1.2
Summary: A puzzle.
Home-page: https://gitlab.com/eklenske/kurzgesagt
Author: Carl Friedrich
Author-email: carl-friedrich@mailbox.org
Keywords: puzzle
Classifier: Development Status :: 3 - Alpha
Classifier: Intended Audience :: Education
Classifier: Programming Language :: Python :: 3 :: Only
Requires-Python: >=3.5, <4
Provides-Extra: dev
Requires-Dist: black ; extra == 'dev'
Requires-Dist: isort ; extra == 'dev'
Requires-Dist: pylint ; extra == 'dev'
Requires-Dist: rope ; extra == 'dev'
